{
  "success": true,
  "data": {
    "topicList": [
      {
        "id": 1,
        "title": "刘备",
        "imageUrl": "http://www.sanguosha.com/uploads/201610/580dbfea5d651.jpg"
      },
      {
        "id": 2,
        "title": "诸葛亮",
        "imageUrl": "http://www.sanguosha.com/uploads/201610/580f157998cab.jpg"
      },
      {
        "id": 3,
        "title": "关羽",
        "imageUrl": "http://www.sanguosha.com/uploads/201610/580f092679ca9.jpg"
      },
      {
        "id": 4,
        "title": "张飞",
        "imageUrl": "http://www.sanguosha.com/uploads/201610/580f1188f0be5.jpg"
      },
      {
        "id": 5,
        "title": "赵云",
        "imageUrl": "http://club.sanguosha.com/data/attachment/forum/201610/04/053756e7jsdej92dlqu2sy.jpg"
      },
      {
        "id": 6,
        "title": "马超",
        "imageUrl": "http://www.sanguosha.com/uploads/201610/580f1acec85e1.jpg"
      },
      {
        "id": 7,
        "title": "黄忠",
        "imageUrl": "http://www.sanguosha.com/uploads/201610/58101b3fc2839.jpg"
      }
    ]
  }
}
